{
  "url": "http://landbot.io",
  "title": "KFUND.VC",
  "description": "Potenciamos la transformación del ecosistema tecnológico español",
  "logo": "files/logo.png",
  "tagline": "KFUND.VC",
  "btn01Title": "Features",
  "btn01Message": "features",
  "btn02Title": "Early Access",
  "btn02Message": "signup",
  "background-video": true,
  "prodID": "230",
  "prodToken": "H-54-05SUR4YA8IFUTM2S",
  "prodApikey": "AIzaSyDsVTr4OpOV45cfIXxcV1UvAEQ6JjnMbZU",
  "testID": "240",
  "testToken": "H-68-AH2T7T2N58350CGU",
  "testApikey": "AIzaSyDsVTr4OpOV45cfIXxcV1UvAEQ6JjnMbZU"
}
